cdktf_cdktf_provider_docker/__init__.py
cdktf_cdktf_provider_docker/py.typed
cdktf_cdktf_provider_docker/_jsii/__init__.py
cdktf_cdktf_provider_docker/_jsii/provider-docker@12.0.2.jsii.tgz
cdktf_cdktf_provider_docker/buildx_builder/__init__.py
cdktf_cdktf_provider_docker/config/__init__.py
cdktf_cdktf_provider_docker/container/__init__.py
cdktf_cdktf_provider_docker/data_docker_image/__init__.py
cdktf_cdktf_provider_docker/data_docker_logs/__init__.py
cdktf_cdktf_provider_docker/data_docker_network/__init__.py
cdktf_cdktf_provider_docker/data_docker_plugin/__init__.py
cdktf_cdktf_provider_docker/data_docker_registry_image/__init__.py
cdktf_cdktf_provider_docker/data_docker_registry_image_manifests/__init__.py
cdktf_cdktf_provider_docker/image/__init__.py
cdktf_cdktf_provider_docker/network/__init__.py
cdktf_cdktf_provider_docker/plugin/__init__.py
cdktf_cdktf_provider_docker/provider/__init__.py
cdktf_cdktf_provider_docker/registry_image/__init__.py
cdktf_cdktf_provider_docker/secret/__init__.py
cdktf_cdktf_provider_docker/service/__init__.py
cdktf_cdktf_provider_docker/tag/__init__.py
cdktf_cdktf_provider_docker/volume/__init__.py
cdktf_cdktf_provider_docker-12.0.2.dist-info/LICENSE
cdktf_cdktf_provider_docker-12.0.2.dist-info/METADATA
cdktf_cdktf_provider_docker-12.0.2.dist-info/WHEEL
cdktf_cdktf_provider_docker-12.0.2.dist-info/top_level.txt
cdktf_cdktf_provider_docker-12.0.2.dist-info/RECORD
